oauthlib/__init__.py
oauthlib/common.py
oauthlib/signals.py
oauthlib/uri_validate.py
oauthlib/oauth1/__init__.py
oauthlib/oauth1/rfc5849/__init__.py
oauthlib/oauth1/rfc5849/errors.py
oauthlib/oauth1/rfc5849/parameters.py
oauthlib/oauth1/rfc5849/request_validator.py
oauthlib/oauth1/rfc5849/signature.py
oauthlib/oauth1/rfc5849/utils.py
oauthlib/oauth1/rfc5849/endpoints/__init__.py
oauthlib/oauth1/rfc5849/endpoints/access_token.py
oauthlib/oauth1/rfc5849/endpoints/authorization.py
oauthlib/oauth1/rfc5849/endpoints/base.py
oauthlib/oauth1/rfc5849/endpoints/pre_configured.py
oauthlib/oauth1/rfc5849/endpoints/request_token.py
oauthlib/oauth1/rfc5849/endpoints/resource.py
oauthlib/oauth1/rfc5849/endpoints/signature_only.py
oauthlib/oauth2/__init__.py
oauthlib/oauth2/rfc6749/__init__.py
oauthlib/oauth2/rfc6749/errors.py
oauthlib/oauth2/rfc6749/parameters.py
oauthlib/oauth2/rfc6749/request_validator.py
oauthlib/oauth2/rfc6749/tokens.py
oauthlib/oauth2/rfc6749/utils.py
oauthlib/oauth2/rfc6749/clients/__init__.py
oauthlib/oauth2/rfc6749/clients/backend_application.py
oauthlib/oauth2/rfc6749/clients/base.py
oauthlib/oauth2/rfc6749/clients/legacy_application.py
oauthlib/oauth2/rfc6749/clients/mobile_application.py
oauthlib/oauth2/rfc6749/clients/service_application.py
oauthlib/oauth2/rfc6749/clients/web_application.py
oauthlib/oauth2/rfc6749/endpoints/__init__.py
oauthlib/oauth2/rfc6749/endpoints/authorization.py
oauthlib/oauth2/rfc6749/endpoints/base.py
oauthlib/oauth2/rfc6749/endpoints/introspect.py
oauthlib/oauth2/rfc6749/endpoints/metadata.py
oauthlib/oauth2/rfc6749/endpoints/pre_configured.py
oauthlib/oauth2/rfc6749/endpoints/resource.py
oauthlib/oauth2/rfc6749/endpoints/revocation.py
oauthlib/oauth2/rfc6749/endpoints/token.py
oauthlib/oauth2/rfc6749/grant_types/__init__.py
oauthlib/oauth2/rfc6749/grant_types/authorization_code.py
oauthlib/oauth2/rfc6749/grant_types/base.py
oauthlib/oauth2/rfc6749/grant_types/client_credentials.py
oauthlib-3.2.1.dist-info/LICENSE
oauthlib-3.2.1.dist-info/METADATA
oauthlib-3.2.1.dist-info/WHEEL
oauthlib-3.2.1.dist-info/top_level.txt
oauthlib-3.2.1.dist-info/RECORD
